arbitration_graphs/__init__.py
arbitration_graphs/__init__.pyi
arbitration_graphs/arbitration_graphs_py.cpython-39-x86_64-linux-gnu.so
arbitration_graphs/py.typed
arbitration_graphs/typing/__init__.py
arbitration_graphs/verification/__init__.py
arbitration_graphs/verification/__init__.pyi
arbitration_graphs.libs/libyaml-cpp-7b41d1a9.so.0.6.2
arbitration_graphs-1.0.0.dist-info/METADATA
arbitration_graphs-1.0.0.dist-info/WHEEL
arbitration_graphs-1.0.0.dist-info/RECORD
