Metadata-Version: 2.2
Name: arbitration_graphs
Version: 1.0.0
Summary: Hierarchical behavior models for complex decision-making and behavior generation in robotics
Keywords: robotics,decision-making,behavior generation,hierarchical behavior models
Author: Christoph Burger, Piotr Spieker, Nick Le Large
Maintainer: Piotr Spieker, Nick Le Large
License: MIT
Project-URL: Homepage, https://kit-mrt.github.io/arbitration_graphs/
Project-URL: Repository, https://github.com/KIT-MRT/arbitration_graphs
Project-URL: Issues, https://github.com/KIT-MRT/arbitration_graphs/issues
Requires-Python: >=3.8
Requires-Dist: pyyaml
Requires-Dist: typing-extensions
